{
  "records": [
    {
      "id": "LDsuxuOL",
      "title": "updatedNew",
      "artist": "updatedArtist",
      "year": 2021,
      "image": "www.",
      "price": 2921
    },
    {
      "id": "lzgRzdPs",
      "title": "updatedNew",
      "artist": "updatedArtist",
      "year": 2021,
      "image": "www.",
      "price": 2921
    },
    {
      "id": "sLrZWPkF",
      "title": "updatedNew",
      "artist": "updatedArtist",
      "year": 2021,
      "image": "www.",
      "price": 2921
    },
    {
      "id": "42K9GI9vf",
      "title": "updatedNew",
      "artist": "updatedArtist",
      "year": 2021,
      "image": "www.",
      "price": 2921
    },
    {
      "id": "sg5u85me",
      "title": "NEW1",
      "artist": "NEW1",
      "year": 2020,
      "image": "www.",
      "price": 2929
    },
    {
      "id": "faaizowC",
      "title": "NEW1",
      "artist": "NEW1",
      "year": 2020,
      "image": "www.",
      "price": 2929
    },
    {
      "id": "fT6wzHpt",
      "title": "NEW1",
      "artist": "NEW1",
      "year": 2020,
      "image": "www.",
      "price": 2929
    },
    {
      "id": "LukCveYV",
      "title": "NEW1",
      "artist": "NEW1",
      "year": 2020,
      "image": "www.",
      "price": 2929
    },
    {
      "id": "7jbCAWm0",
      "title": "NEW1",
      "artist": "NEW1",
      "year": 2020,
      "image": "www.",
      "price": 2929
    },
    {
      "id": "72WHL6cE8",
      "title": "NEW1",
      "artist": "NEW1",
      "year": 2020,
      "image": "www.",
      "price": 2929
    },
    {
      "id": "E_z8ldPR",
      "title": "NEW1",
      "artist": "NEW1",
      "year": 2020,
      "image": "www.",
      "price": 2929
    },
    {
      "id": "-04ZbsKh",
      "title": "NEW1",
      "artist": "NEW1",
      "year": 2020,
      "image": "www.",
      "price": 2929
    },
    {
      "id": "qxKMQ6Ml",
      "title": "NEW1",
      "artist": "NEW1",
      "year": 2020,
      "image": "www.",
      "price": 2929
    },
    {
      "id": "4jM80KyP",
      "title": "NEW1",
      "artist": "NEW1",
      "year": 2020,
      "image": "www.",
      "price": 2929
    },
    {
      "id": "Z3kFOM-F",
      "title": "NEW1",
      "artist": "NEW1",
      "year": 2020,
      "image": "www.",
      "price": 2929
    },
    {
      "id": "wbN4yNPN",
      "title": "NEW1",
      "artist": "NEW1",
      "year": 2020,
      "image": "www.",
      "price": 2929
    },
    {
      "id": "NWe5HulY",
      "title": "NEW1",
      "artist": "NEW1",
      "year": 2020,
      "image": "www.",
      "price": 2929
    },
    {
      "id": "6c2MXXRf",
      "title": "Song",
      "artist": "Bob",
      "year": 2021,
      "image": "www.",
      "price": 2921
    },
    {
      "id": "iBo6rB2m",
      "title": "Maxim",
      "artist": "Bob",
      "year": 2021,
      "image": "www.",
      "price": 2921
    }
  ]
}